brkraw_sordino/__init__.py
brkraw_sordino/brkraw_hook.yaml
brkraw_sordino/docs.md
brkraw_sordino/helper.py
brkraw_sordino/hook.py
brkraw_sordino/orientation.py
brkraw_sordino/recon.py
brkraw_sordino/spoketiming.py
brkraw_sordino/traj.py
brkraw_sordino/typing.py
brkraw_sordino/rules/sordino.yaml
brkraw_sordino/specs/info_spec.yaml
brkraw_sordino/specs/metadata_spec.yaml
brkraw_sordino/specs/prune4recon.yaml
brkraw_sordino/specs/recon_spec.yaml
brkraw_sordino/specs/utils.py
brkraw_sordino-0.2.4.dist-info/METADATA
brkraw_sordino-0.2.4.dist-info/WHEEL
brkraw_sordino-0.2.4.dist-info/entry_points.txt
brkraw_sordino-0.2.4.dist-info/top_level.txt
brkraw_sordino-0.2.4.dist-info/RECORD
