Metadata-Version: 2.4
Name: brkraw-sordino
Version: 0.2.4
Summary: BrkRaw converter hook for SORDINO-ZTE reconstruction
Author-email: SungHo Lee <shlee@unc.edu>
License: MIT
Requires-Python: >=3.10
Requires-Dist: brkraw
Requires-Dist: numpy
Requires-Dist: scipy
Requires-Dist: mri-nufft[finufft]
Provides-Extra: dev
Requires-Dist: tomli; extra == "dev"
